{
  "clientId": 3590,
  "clientName": "MAISON DESPRIET SA",
  "orderName": "S40210",
  "orderDate": "2025-11-07 12:48:24",
  "cutoffDate": "2025-11-06 00:00:00",
  "daysBeforePrediction": 1,
  "metrics": {
    "tp": 5,
    "fp": 3,
    "fn": 0,
    "precision": 0.625,
    "recall": 1,
    "f1Score": 0.7692307692307693,
    "mae": 81,
    "wmape": 51.071878940731395,
    "mape": 42.5,
    "bias": -51.071878940731395
  },
  "distribution": {
    "exactMatch": 1,
    "partialMatch": 4
  },
  "llmUsage": {
    "calls": 10,
    "promptTokens": 22872,
    "completionTokens": 30198,
    "totalTokens": 53070
  }
}