{
  "clientId": 9942,
  "clientName": "La fermette",
  "orderName": "S40013",
  "orderDate": "2025-10-30 07:17:13",
  "cutoffDate": "2025-10-29 00:00:00",
  "daysBeforePrediction": 1,
  "metrics": {
    "tp": 13,
    "fp": 22,
    "fn": 0,
    "precision": 0.37142857142857144,
    "recall": 1,
    "f1Score": 0.5416666666666666,
    "mae": 0.23076923076923078,
    "wmape": 21.428571428571427,
    "mape": 19.23076923076923,
    "bias": 7.142857142857142
  },
  "distribution": {
    "exactMatch": 10,
    "partialMatch": 3
  },
  "llmUsage": {
    "calls": 26,
    "promptTokens": 20088,
    "completionTokens": 6390,
    "totalTokens": 26478
  }
}