{
  "clientId": 60508,
  "clientName": "PAIRI DAIZA stock",
  "orderName": "S39785",
  "orderDate": "2025-10-21 07:58:15",
  "cutoffDate": "2025-10-20 00:00:00",
  "daysBeforePrediction": 1,
  "metrics": {
    "tp": 4,
    "fp": 1,
    "fn": 0,
    "precision": 0.8,
    "recall": 1,
    "f1Score": 0.888888888888889,
    "mae": 6.25,
    "wmape": 69.44444444444444,
    "mape": 58.33333333333333,
    "bias": 36.11111111111111
  },
  "distribution": {
    "exactMatch": 0,
    "partialMatch": 4
  },
  "llmUsage": {
    "calls": 5,
    "promptTokens": 4549,
    "completionTokens": 863,
    "totalTokens": 5412
  }
}