{
  "clientId": 134,
  "clientName": "Le bon Wagon Malmedy",
  "orderName": "S39602",
  "orderDate": "2025-10-08 07:14:28",
  "cutoffDate": "2025-10-07 00:00:00",
  "daysBeforePrediction": 1,
  "metrics": {
    "tp": 5,
    "fp": 3,
    "fn": 0,
    "precision": 0.625,
    "recall": 1,
    "f1Score": 0.7692307692307693,
    "mae": 3.2,
    "wmape": 72.72727272727273,
    "mape": 64,
    "bias": -72.72727272727273
  },
  "distribution": {
    "exactMatch": 1,
    "partialMatch": 4
  },
  "llmUsage": {
    "calls": 25,
    "promptTokens": 21883,
    "completionTokens": 3425,
    "totalTokens": 25308
  }
}