{
  "clientId": 9942,
  "clientName": "La fermette",
  "orderName": "S40013",
  "orderDate": "2025-10-30 07:17:13",
  "cutoffDate": "2025-10-29 00:00:00",
  "daysBeforePrediction": 1,
  "metrics": {
    "tp": 14,
    "fp": 29,
    "fn": 0,
    "precision": 0.32558139534883723,
    "recall": 1,
    "f1Score": 0.49122807017543857,
    "mae": 0.07142857142857142,
    "wmape": 6.666666666666667,
    "mape": 3.5714285714285716,
    "bias": -6.666666666666667
  },
  "distribution": {
    "exactMatch": 13,
    "partialMatch": 1
  },
  "llmUsage": {
    "calls": 48,
    "promptTokens": 43625,
    "completionTokens": 7146,
    "totalTokens": 50771
  }
}