{
  "meta": {
    "version": "2.0.0",
    "generatedAt": "2025-12-30T14:28:35.156Z",
    "config": {
      "daysBeforePrediction": 1,
      "analysisWindowDays": 365,
      "cutoffDate": "2025-11-13 00:00:00"
    }
  },
  "client": {
    "id": 24360,
    "name": "La fromagerie des 2 Monts",
    "order": {
      "name": "S40245",
      "date": "2025-11-14 12:30:40"
    }
  },
  "metrics": {
    "all": {
      "counts": {
        "truePositives": 0,
        "falsePositives": 0,
        "falseNegatives": 6,
        "total": 6
      },
      "productMetrics": {
        "precision": 0,
        "recall": 0,
        "f1Score": 0,
        "totalPredicted": 0,
        "totalReal": 6
      },
      "quantityMetrics": {
        "mae": 0,
        "wmape": 0,
        "mape": 0,
        "bias": 0,
        "distribution": {
          "exactMatch": 0,
          "partialMatch": 0
        },
        "rmse": 0
      }
    },
    "byConfidence": {
      "low": {
        "counts": {
          "truePositives": 0,
          "falsePositives": 0,
          "falseNegatives": 6,
          "total": 6
        },
        "productMetrics": {
          "precision": 0,
          "recall": 0,
          "f1Score": 0,
          "totalPredicted": 0,
          "totalReal": 6
        },
        "quantityMetrics": {
          "mae": 0,
          "wmape": 0,
          "mape": 0,
          "bias": 0,
          "distribution": {
            "exactMatch": 0,
            "partialMatch": 0
          },
          "rmse": 0
        }
      },
      "medium": {
        "counts": {
          "truePositives": 0,
          "falsePositives": 0,
          "falseNegatives": 0,
          "total": 0
        },
        "productMetrics": {
          "precision": 0,
          "recall": 0,
          "f1Score": 0,
          "totalPredicted": 0,
          "totalReal": 0
        },
        "quantityMetrics": {
          "mae": 0,
          "wmape": 0,
          "mape": 0,
          "bias": 0,
          "distribution": {
            "exactMatch": 0,
            "partialMatch": 0
          },
          "rmse": 0
        }
      },
      "high": {
        "counts": {
          "truePositives": 0,
          "falsePositives": 0,
          "falseNegatives": 0,
          "total": 0
        },
        "productMetrics": {
          "precision": 0,
          "recall": 0,
          "f1Score": 0,
          "totalPredicted": 0,
          "totalReal": 0
        },
        "quantityMetrics": {
          "mae": 0,
          "wmape": 0,
          "mape": 0,
          "bias": 0,
          "distribution": {
            "exactMatch": 0,
            "partialMatch": 0
          },
          "rmse": 0
        }
      }
    }
  },
  "products": {
    "truePositives": [],
    "falsePositives": [],
    "falseNegatives": [
      {
        "productId": 13058,
        "productName": "[LV160] LV Tartinade Aubergine 190g",
        "mismatchType": "false_negative",
        "quantity": 3,
        "reason": "Never ordered in previous analysis window (no history)",
        "classification": {
          "category": "other",
          "severity": "low"
        }
      },
      {
        "productId": 13060,
        "productName": "[LV161] LV Tartinade Mangue curry 190g",
        "mismatchType": "false_negative",
        "quantity": 3,
        "reason": "Never ordered in previous analysis window (no history)",
        "classification": {
          "category": "other",
          "severity": "low"
        }
      },
      {
        "productId": 13061,
        "productName": "[LV130] LV BIO Tartinade Paprika Chili 190g",
        "mismatchType": "false_negative",
        "quantity": 3,
        "reason": "Never ordered in previous analysis window (no history)",
        "classification": {
          "category": "other",
          "severity": "low"
        }
      },
      {
        "productId": 13063,
        "productName": "[LV132] LV Tartinade Houmous type 190g",
        "mismatchType": "false_negative",
        "quantity": 3,
        "reason": "Never ordered in previous analysis window (no history)",
        "classification": {
          "category": "other",
          "severity": "low"
        }
      },
      {
        "productId": 13064,
        "productName": "[LV162] LV Tartinade Tomato Basilico 190g",
        "mismatchType": "false_negative",
        "quantity": 3,
        "reason": "Never ordered in previous analysis window (no history)",
        "classification": {
          "category": "other",
          "severity": "low"
        }
      },
      {
        "productId": 14452,
        "productName": "[LV332] LV Tartinade Olive Caper Tomato 190g",
        "mismatchType": "false_negative",
        "quantity": 3,
        "reason": "Never ordered in previous analysis window (no history)",
        "classification": {
          "category": "other",
          "severity": "low"
        }
      }
    ]
  }
}