{
  "meta": {
    "version": "2.0.0",
    "generatedAt": "2025-12-30T14:24:06.942Z",
    "config": {
      "daysBeforePrediction": 1,
      "analysisWindowDays": 365,
      "cutoffDate": "2025-11-03 00:00:00"
    }
  },
  "client": {
    "id": 3543,
    "name": "YUGO SNACK",
    "order": {
      "name": "S40099",
      "date": "2025-11-04 09:01:57"
    }
  },
  "metrics": {
    "all": {
      "counts": {
        "truePositives": 0,
        "falsePositives": 0,
        "falseNegatives": 1,
        "total": 1
      },
      "productMetrics": {
        "precision": 0,
        "recall": 0,
        "f1Score": 0,
        "totalPredicted": 0,
        "totalReal": 1
      },
      "quantityMetrics": {
        "mae": 0,
        "wmape": 0,
        "mape": 0,
        "bias": 0,
        "distribution": {
          "exactMatch": 0,
          "partialMatch": 0
        },
        "rmse": 0
      }
    },
    "byConfidence": {
      "low": {
        "counts": {
          "truePositives": 0,
          "falsePositives": 0,
          "falseNegatives": 1,
          "total": 1
        },
        "productMetrics": {
          "precision": 0,
          "recall": 0,
          "f1Score": 0,
          "totalPredicted": 0,
          "totalReal": 1
        },
        "quantityMetrics": {
          "mae": 0,
          "wmape": 0,
          "mape": 0,
          "bias": 0,
          "distribution": {
            "exactMatch": 0,
            "partialMatch": 0
          },
          "rmse": 0
        }
      },
      "medium": {
        "counts": {
          "truePositives": 0,
          "falsePositives": 0,
          "falseNegatives": 0,
          "total": 0
        },
        "productMetrics": {
          "precision": 0,
          "recall": 0,
          "f1Score": 0,
          "totalPredicted": 0,
          "totalReal": 0
        },
        "quantityMetrics": {
          "mae": 0,
          "wmape": 0,
          "mape": 0,
          "bias": 0,
          "distribution": {
            "exactMatch": 0,
            "partialMatch": 0
          },
          "rmse": 0
        }
      },
      "high": {
        "counts": {
          "truePositives": 0,
          "falsePositives": 0,
          "falseNegatives": 0,
          "total": 0
        },
        "productMetrics": {
          "precision": 0,
          "recall": 0,
          "f1Score": 0,
          "totalPredicted": 0,
          "totalReal": 0
        },
        "quantityMetrics": {
          "mae": 0,
          "wmape": 0,
          "mape": 0,
          "bias": 0,
          "distribution": {
            "exactMatch": 0,
            "partialMatch": 0
          },
          "rmse": 0
        }
      }
    }
  },
  "products": {
    "truePositives": [],
    "falsePositives": [],
    "falseNegatives": [
      {
        "productId": 9004,
        "productName": "[PF0162] MOUTARDE JAUNE VRAC",
        "mismatchType": "false_negative",
        "quantity": 1795,
        "reason": "Never ordered in previous analysis window (no history)",
        "classification": {
          "category": "other",
          "severity": "high"
        }
      }
    ]
  }
}