{
  "clientId": 38995,
  "clientName": "MASETTI",
  "orderName": "S39608",
  "orderDate": "2025-10-08 06:19:58",
  "cutoffDate": "2025-10-07 00:00:00",
  "daysBeforePrediction": 1,
  "metrics": {
    "tp": 23,
    "fp": 5,
    "fn": 1,
    "precision": 0.8214285714285714,
    "recall": 0.9583333333333334,
    "f1Score": 0.8846153846153847,
    "mae": 3.652173913043478,
    "wmape": 35,
    "mape": 64.20289855072463,
    "bias": 9.166666666666666
  },
  "distribution": {
    "exactMatch": 8,
    "partialMatch": 15
  },
  "llmUsage": {
    "calls": 18,
    "promptTokens": 28871,
    "completionTokens": 6130,
    "totalTokens": 35001
  }
}