{
  "clientId": 3547,
  "clientName": "K&F DE PAUW",
  "orderName": "S40269",
  "orderDate": "2025-11-12 11:39:39",
  "cutoffDate": "2025-11-11 00:00:00",
  "daysBeforePrediction": 1,
  "metrics": {
    "tp": 1,
    "fp": 13,
    "fn": 0,
    "precision": 0.07142857142857142,
    "recall": 1,
    "f1Score": 0.13333333333333333,
    "mae": 78,
    "wmape": 48.75,
    "mape": 48.75,
    "bias": -48.75
  },
  "distribution": {
    "exactMatch": 0,
    "partialMatch": 1
  },
  "llmUsage": {
    "calls": 20,
    "promptTokens": 44179,
    "completionTokens": 147961,
    "totalTokens": 192140
  }
}