{
  "clientId": 5490,
  "clientName": "BIOCOOP SA COOP, BIOCOOP SA COOP, Adresse de facturation",
  "orderName": "S39754",
  "orderDate": "2025-10-16 06:33:00",
  "cutoffDate": "2025-10-15 00:00:00",
  "daysBeforePrediction": 1,
  "metrics": {
    "tp": 10,
    "fp": 9,
    "fn": 0,
    "precision": 0.5263157894736842,
    "recall": 1,
    "f1Score": 0.6896551724137931,
    "mae": 80.3,
    "wmape": 45.676905574516496,
    "mape": 66.66666666666666,
    "bias": 45.676905574516496
  },
  "distribution": {
    "exactMatch": 3,
    "partialMatch": 7
  },
  "llmUsage": {
    "calls": 25,
    "promptTokens": 28110,
    "completionTokens": 65798,
    "totalTokens": 93908
  }
}