{
  "clientId": 58284,
  "clientName": "SPRL GOOD & FOOD",
  "orderName": "S39546",
  "orderDate": "2025-10-03 12:32:05",
  "cutoffDate": "2025-10-02 00:00:00",
  "daysBeforePrediction": 1,
  "metrics": {
    "tp": 3,
    "fp": 4,
    "fn": 0,
    "precision": 0.42857142857142855,
    "recall": 1,
    "f1Score": 0.6,
    "mae": 4.333333333333333,
    "wmape": 3.6211699164345403,
    "mape": 3.526686217008798,
    "bias": 3.6211699164345403
  },
  "distribution": {
    "exactMatch": 0,
    "partialMatch": 3
  },
  "llmUsage": {
    "calls": 7,
    "promptTokens": 10012,
    "completionTokens": 1913,
    "totalTokens": 11925
  }
}